INEX/AI.py
INEX/Crypto.py
INEX/Database.py
INEX/EnDeCrypt.py
INEX/FastAPIServer.py
INEX/Files.py
INEX/Libraries.py
INEX/PrintStyle.py
INEX/Security.py
INEX/Server.py
INEX/System.py
INEX/Translate.py
INEX/VideosCreator.py
INEX/Websites.py
INEX/__init__.py
inex_library-1.0.1.dist-info/LICENSE
inex_library-1.0.1.dist-info/METADATA
inex_library-1.0.1.dist-info/WHEEL
inex_library-1.0.1.dist-info/top_level.txt
inex_library-1.0.1.dist-info/RECORD
