Metadata-Version: 2.2
Name: inex-library
Version: 1.0.1
Summary: A comprehensive Python library for AI integration, web development with FastAPI/Flask, advanced encryption, secure database management, file operations, library development, text styling, system management, translation services, video creation, web automation, and cryptocurrency token analysis. Features include JWT handling, password management, rate limiting, input sanitization, and more.
Home-page: https://github.com/AmmarBasha2011/inex_library
Author: INEX Team
Author-email: pbstzidr@ywp.freewebhostmost.com
Project-URL: Documentation, https://pypi.org/project/inex
Project-URL: Source, https://github.com/AmmarBasha2011/inex_library
Project-URL: Tracker, https://github.com/AmmarBasha2011/inex_library/issues
Project-URL: Download, https://pypi.org/project/inex#files
Keywords: ai,gemini,chatgpt,deepseek,web development,fastapi,asgi,server,cors,uvicorn,encryption,aes,blowfish,base64,secure database,sqlite,sqlcipher,flask,crypto,security,blockchain,binance,ethereum,cryptocurrency,file management,file operations,library development,package distribution,text styling,terminal output,jwt,password,rate limiting,input sanitization,2fa,authentication,wsgi,asgi,gunicorn,nginx,system management,process control,hardware monitoring,translation,language detection,nlp,vide
Classifier: Development Status :: 5 - Production/Stable
Classifier: Intended Audience :: Developers
Classifier: License :: OSI Approved :: MIT License
Classifier: Programming Language :: Python :: 3
Classifier: Programming Language :: Python :: 3.7
Classifier: Programming Language :: Python :: 3.8
Classifier: Programming Language :: Python :: 3.9
Classifier: Programming Language :: Python :: 3.10
Classifier: Programming Language :: Python :: 3.11
Classifier: Operating System :: OS Independent
Classifier: Topic :: Software Development :: Libraries :: Python Modules
Classifier: Topic :: Internet :: WWW/HTTP
Classifier: Topic :: Internet :: WWW/HTTP :: Dynamic Content
Classifier: Topic :: Internet :: WWW/HTTP :: WSGI
Classifier: Topic :: Security :: Cryptography
Classifier: Topic :: Database
Classifier: Topic :: System :: Systems Administration
Classifier: Topic :: Text Processing :: General
Classifier: Topic :: Software Development :: Libraries
Classifier: Topic :: Software Development :: Build Tools
Classifier: Topic :: Software Development :: User Interfaces
Classifier: Topic :: System :: Installation/Setup
Classifier: Topic :: System :: Software Distribution
Classifier: Topic :: System :: Systems Administration
Classifier: Topic :: Text Processing :: General
Classifier: Topic :: Utilities
Classifier: Natural Language :: English
Classifier: Natural Language :: Arabic
Classifier: Natural Language :: Chinese (Simplified)
Classifier: Natural Language :: French
Classifier: Natural Language :: German
Classifier: Natural Language :: Italian
Classifier: Natural Language :: Japanese
Classifier: Natural Language :: Korean
Classifier: Natural Language :: Portuguese
Classifier: Natural Language :: Russian
Classifier: Natural Language :: Spanish
Classifier: Topic :: Multimedia :: Video
Classifier: Topic :: Multimedia :: Graphics
Classifier: Topic :: Internet :: WWW/HTTP :: Browsers
Classifier: Framework :: FastAPI
Classifier: Framework :: Flask
Requires-Python: >=3.7
License-File: LICENSE
Requires-Dist: fastapi>=0.68.0
Requires-Dist: uvicorn>=0.15.0
Requires-Dist: starlette>=0.14.0
Requires-Dist: pydantic>=1.8.0
Requires-Dist: flask>=2.0.0
Requires-Dist: pycryptodome>=3.10.0
Requires-Dist: cryptography>=3.4.0
Requires-Dist: requests>=2.26.0
Requires-Dist: openai>=1.0.0
Requires-Dist: python-jose>=3.3.0
Requires-Dist: passlib>=1.7.4
Requires-Dist: pyjwt>=2.1.0
Requires-Dist: pynacl>=1.4.0
Requires-Dist: python-multipart>=0.0.5
Requires-Dist: python-dotenv>=0.19.0
Requires-Dist: aiofiles>=0.7.0
Requires-Dist: watchdog>=2.1.0
Requires-Dist: pathlib>=1.0.1
Requires-Dist: pyotp>=2.6.0
Requires-Dist: moviepy>=1.0.3
Requires-Dist: googletrans>=3.1.0a0
Requires-Dist: pillow>=8.3.0
Requires-Dist: web3>=5.24.0
Requires-Dist: sqlalchemy>=1.4.0
Requires-Dist: alembic>=1.7.0
Requires-Dist: sqlcipher3>=0.4.5
Requires-Dist: twine>=3.4.2
Requires-Dist: wheel>=0.37.0
Requires-Dist: setuptools>=57.0.0
Requires-Dist: build>=0.7.0
Requires-Dist: colorama>=0.4.4
Requires-Dist: termcolor>=1.1.0
Requires-Dist: rich>=10.12.0
Requires-Dist: bcrypt>=3.2.0
Requires-Dist: pyOpenSSL>=20.0.0
Requires-Dist: cryptography-vectors>=3.4.0
Requires-Dist: python-magic>=0.4.24
Requires-Dist: redis>=4.0.0
Requires-Dist: bleach>=4.1.0
Requires-Dist: validators>=0.18.0
Requires-Dist: gunicorn>=20.1.0
Requires-Dist: hypercorn>=0.11.0
Requires-Dist: werkzeug>=2.0.0
Requires-Dist: click>=8.0.0
Requires-Dist: jinja2>=3.0.0
Requires-Dist: itsdangerous>=2.0.0
Requires-Dist: psutil>=5.8.0
Requires-Dist: pywin32>=300; platform_system == "Windows"
Requires-Dist: pyuac>=0.0.3; platform_system == "Windows"
Requires-Dist: elevate>=0.1.3
Requires-Dist: opencv-python>=4.5.0
Requires-Dist: numpy>=1.21.0
Requires-Dist: ffmpeg-python>=0.2.0
Requires-Dist: beautifulsoup4>=4.9.0
Requires-Dist: selenium>=4.0.0
Requires-Dist: playwright>=1.20.0
Requires-Dist: urllib3>=1.26.0
Requires-Dist: aiohttp>=3.8.0
Requires-Dist: httpx>=0.23.0
Provides-Extra: dev
Requires-Dist: pytest>=6.2.0; extra == "dev"
Requires-Dist: black>=21.7b0; extra == "dev"
Requires-Dist: isort>=5.9.0; extra == "dev"
Requires-Dist: flake8>=3.9.0; extra == "dev"
Requires-Dist: httpx>=0.18.0; extra == "dev"
Requires-Dist: pytest-asyncio>=0.15.0; extra == "dev"
Requires-Dist: safety>=1.10.0; extra == "dev"
Requires-Dist: bandit>=1.7.0; extra == "dev"
Requires-Dist: locust>=2.8.0; extra == "dev"
Requires-Dist: coverage>=6.2; extra == "dev"
Requires-Dist: pytest-cov>=3.0.0; extra == "dev"
Provides-Extra: database
Requires-Dist: psycopg2-binary>=2.9.0; extra == "database"
Requires-Dist: pymysql>=1.0.0; extra == "database"
Requires-Dist: sqlcipher3>=0.4.5; extra == "database"
Requires-Dist: cryptography>=3.4.0; extra == "database"
Provides-Extra: crypto
Requires-Dist: pyOpenSSL>=20.0.0; extra == "crypto"
Requires-Dist: cryptography-vectors>=3.4.0; extra == "crypto"
Requires-Dist: bcrypt>=3.2.0; extra == "crypto"
Requires-Dist: pynacl>=1.4.0; extra == "crypto"
Requires-Dist: pyotp>=2.6.0; extra == "crypto"
Requires-Dist: qrcode>=7.3.0; extra == "crypto"
Provides-Extra: server
Requires-Dist: gunicorn>=20.1.0; extra == "server"
Requires-Dist: hypercorn>=0.11.0; extra == "server"
Requires-Dist: fastapi-utils>=0.2.0; extra == "server"
Requires-Dist: fastapi-jwt-auth>=0.5.0; extra == "server"
Requires-Dist: fastapi-cache>=0.1.0; extra == "server"
Requires-Dist: fastapi-limiter>=0.1.5; extra == "server"
Requires-Dist: secure>=0.3.0; extra == "server"
Requires-Dist: flask-cors>=3.0.0; extra == "server"
Requires-Dist: flask-compress>=1.10.0; extra == "server"
Requires-Dist: flask-caching>=1.10.0; extra == "server"
Requires-Dist: flask-limiter>=2.5.0; extra == "server"
Requires-Dist: flask-talisman>=0.8.0; extra == "server"
Requires-Dist: flask-seasurf>=0.3.0; extra == "server"
Requires-Dist: prometheus-flask-exporter>=0.18.0; extra == "server"
Requires-Dist: sentry-sdk>=1.5.0; extra == "server"
Requires-Dist: supervisor>=4.2.0; extra == "server"
Requires-Dist: nginx>=1.20.0; extra == "server"
Provides-Extra: files
Requires-Dist: watchdog>=2.1.0; extra == "files"
Requires-Dist: pathlib>=1.0.1; extra == "files"
Requires-Dist: send2trash>=1.8.0; extra == "files"
Requires-Dist: python-magic>=0.4.24; extra == "files"
Requires-Dist: aiofiles>=0.7.0; extra == "files"
Requires-Dist: filetype>=1.0.0; extra == "files"
Provides-Extra: packaging
Requires-Dist: twine>=3.4.2; extra == "packaging"
Requires-Dist: wheel>=0.37.0; extra == "packaging"
Requires-Dist: build>=0.7.0; extra == "packaging"
Requires-Dist: check-manifest>=0.47.0; extra == "packaging"
Requires-Dist: readme-renderer>=29.0; extra == "packaging"
Requires-Dist: keyring>=23.0.1; extra == "packaging"
Provides-Extra: styling
Requires-Dist: colorama>=0.4.4; extra == "styling"
Requires-Dist: termcolor>=1.1.0; extra == "styling"
Requires-Dist: rich>=10.12.0; extra == "styling"
Requires-Dist: blessed>=1.19.0; extra == "styling"
Requires-Dist: prompt-toolkit>=3.0.20; extra == "styling"
Provides-Extra: security
Requires-Dist: cryptography>=3.4.0; extra == "security"
Requires-Dist: pycryptodome>=3.10.0; extra == "security"
Requires-Dist: python-jose>=3.3.0; extra == "security"
Requires-Dist: passlib>=1.7.4; extra == "security"
Requires-Dist: bcrypt>=3.2.0; extra == "security"
Requires-Dist: pyotp>=2.6.0; extra == "security"
Requires-Dist: qrcode>=7.3.0; extra == "security"
Requires-Dist: redis>=4.0.0; extra == "security"
Requires-Dist: bleach>=4.1.0; extra == "security"
Requires-Dist: validators>=0.18.0; extra == "security"
Requires-Dist: secure>=0.3.0; extra == "security"
Requires-Dist: pyOpenSSL>=20.0.0; extra == "security"
Requires-Dist: safety>=1.10.0; extra == "security"
Requires-Dist: bandit>=1.7.0; extra == "security"
Provides-Extra: system
Requires-Dist: psutil>=5.8.0; extra == "system"
Requires-Dist: pywin32>=300; platform_system == "Windows" and extra == "system"
Requires-Dist: pyuac>=0.0.3; platform_system == "Windows" and extra == "system"
Requires-Dist: elevate>=0.1.3; extra == "system"
Requires-Dist: distro>=1.6.0; extra == "system"
Requires-Dist: py-cpuinfo>=8.0.0; extra == "system"
Requires-Dist: gputil>=1.4.0; extra == "system"
Requires-Dist: psutil>=5.8.0; extra == "system"
Requires-Dist: pyusb>=1.2.0; extra == "system"
Requires-Dist: pyserial>=3.5; extra == "system"
Requires-Dist: netifaces>=0.11.0; extra == "system"
Requires-Dist: ifaddr>=0.1.7; extra == "system"
Provides-Extra: translation
Requires-Dist: googletrans>=3.1.0a0; extra == "translation"
Requires-Dist: deep-translator>=1.9.0; extra == "translation"
Requires-Dist: langdetect>=1.0.9; extra == "translation"
Requires-Dist: polyglot>=16.7.4; extra == "translation"
Requires-Dist: textblob>=0.17.1; extra == "translation"
Requires-Dist: mtranslate>=1.8; extra == "translation"
Requires-Dist: textblob>=0.17.1; extra == "translation"
Requires-Dist: lingua>=4.15.0; extra == "translation"
Provides-Extra: video
Requires-Dist: moviepy>=1.0.3; extra == "video"
Requires-Dist: opencv-python>=4.5.0; extra == "video"
Requires-Dist: numpy>=1.21.0; extra == "video"
Requires-Dist: ffmpeg-python>=0.2.0; extra == "video"
Requires-Dist: pillow>=8.3.0; extra == "video"
Requires-Dist: imageio>=2.9.0; extra == "video"
Requires-Dist: imageio-ffmpeg>=0.4.5; extra == "video"
Requires-Dist: scikit-image>=0.18.0; extra == "video"
Requires-Dist: scipy>=1.7.0; extra == "video"
Requires-Dist: av>=9.0.0; extra == "video"
Requires-Dist: python-vlc>=3.0.0; extra == "video"
Requires-Dist: pims>=0.5.0; extra == "video"
Provides-Extra: web
Requires-Dist: beautifulsoup4>=4.9.0; extra == "web"
Requires-Dist: selenium>=4.0.0; extra == "web"
Requires-Dist: playwright>=1.20.0; extra == "web"
Requires-Dist: requests>=2.26.0; extra == "web"
Requires-Dist: urllib3>=1.26.0; extra == "web"
Requires-Dist: aiohttp>=3.8.0; extra == "web"
Requires-Dist: httpx>=0.23.0; extra == "web"
Requires-Dist: html5lib>=1.1; extra == "web"
Requires-Dist: lxml>=4.9.0; extra == "web"
Requires-Dist: webdriver-manager>=3.5.0; extra == "web"
Requires-Dist: pyppeteer>=1.0.0; extra == "web"
Requires-Dist: requests-html>=0.10.0; extra == "web"
Requires-Dist: mechanize>=0.4.0; extra == "web"
Requires-Dist: scrapy>=2.5.0; extra == "web"
Requires-Dist: pyquery>=1.4.0; extra == "web"
Dynamic: author
Dynamic: author-email
Dynamic: classifier
Dynamic: description
Dynamic: description-content-type
Dynamic: home-page
Dynamic: keywords
Dynamic: project-url
Dynamic: provides-extra
Dynamic: requires-dist
Dynamic: requires-python
Dynamic: summary
